grammar_guide/__init__.py
grammar_guide/_logger.py
grammar_guide/guide.py
grammar_guide/typedefs.py
grammar_guide/utils.py
grammar_guide/minEarley/__init__.py
grammar_guide/minEarley/earley.py
grammar_guide/minEarley/earley_analyzer.py
grammar_guide/minEarley/earley_exceptions.py
grammar_guide/minEarley/earley_forest.py
grammar_guide/minEarley/parser.py
grammar_guide/minEarley/tree.py
grammar_guide/minEarley/utils.py
grammar_guide/model/__init__.py
grammar_guide/model/logits_processors.py
grammar_guide/model/modeling_utils.py
grammar_guide-0.0.11.dist-info/LICENSE
grammar_guide-0.0.11.dist-info/METADATA
grammar_guide-0.0.11.dist-info/WHEEL
grammar_guide-0.0.11.dist-info/top_level.txt
grammar_guide-0.0.11.dist-info/RECORD
