Metadata-Version: 2.1
Name: grammar-guide
Version: 0.0.11
Summary: Speculative grammar backtracking algorithm for LLM decoding conforming to some lark context-free grammar (CFG)
Author-email: Parker Glenn <parkervg5@gmail.com>
License: Apache License
Project-URL: Documentation, https://github.com/parkervg/grammar-guide
Keywords: language models,structured generation,constrained decoding,formal grammars
Classifier: Development Status :: 4 - Beta
Classifier: Intended Audience :: Developers
Classifier: Intended Audience :: Science/Research
Classifier: Topic :: Scientific/Engineering :: Artificial Intelligence
Classifier: Topic :: Text Processing
Classifier: Programming Language :: Python :: 3
Requires-Python: >=3.9
License-File: LICENSE
Requires-Dist: guidance >=0.1.16
Requires-Dist: numpy <2
Requires-Dist: exrex
Requires-Dist: lark
Requires-Dist: colorama
Requires-Dist: pygtrie
Requires-Dist: ipython
